{
    "m_name": "move_from",
    "m_args": [
        "to",
        "vase_entertainment_center_coffee_table"
    ],
    "subtasks": [
        {
            "m_name": "GotoLocation",
            "m_args": [
                "shelf"
            ],
            "subtasks": [
                {
                    "s_name": "Navigate",
                    "s_args": [
                        "shelf"
                    ]
                }
            ]
        },
        {
            "m_name": "PickupObject",
            "m_args": [
                "vase"
            ],
            "subtasks": [
                {
                    "s_name": "PickupObject",
                    "s_args": "Vase"
                }
            ]
        },
        {
            "m_name": "GotoLocation",
            "m_args": [
                "coffeetable"
            ],
            "subtasks": [
                {
                    "s_name": "Navigate",
                    "s_args": [
                        "coffeetable"
                    ]
                }
            ]
        },
        {
            "m_name": "PutObject",
            "m_args": [
                "vase",
                "coffeetable"
            ],
            "subtasks": [
                {
                    "s_name": "PutObject",
                    "s_args": [
                        "Vase",
                        "CoffeeTable"
                    ]
                }
            ]
        }
    ]
}